{
  "base_price": 1950,
  "beamstation_catalog_url": "https://beamstation.com/datasets",
  "beamstation_origin": "https://beamstation.com",
  "category_group_name": "Restaurants",
  "config_category": "census",
  "config_description": "Complete dataset of all active restaurant listings in Oakland, California with a population of over 440k. Filtered by the Restaurants category group, this city-level export covers verified business profiles including ratings, reviews, contact details, and competitive metrics for the local dining market. Refreshed weekly.",
  "config_name": "All Restaurants in Oakland, California, US",
  "export_job_id": "1f98b810-68e5-480c-9308-978ab4bca240",
  "github_org": "Beamstation-Datasets",
  "id_short": 420291,
  "location_name": "Oakland",
  "location_type": "city",
  "repo_name": "all-restaurants-in-oakland-california-us-sample-420291",
  "sample_b2_path": "b2-export:BeamStation-ExportFiles/420291/beamstation_420291_restaurants-us-ca_SAMPLE_DIST.csv",
  "sample_pct": 9.95,
  "sample_records": 124,
  "sample_sha256": "06d967e64c056a14c3316354508c6ca2328ead01709d3e961471c62508ed01f6",
  "sample_size_bytes": 465247,
  "total_records": 1246,
  "updated_at": "2026-04-09T14:21:11.844928+00:00"
}